var map = {};
var map1 = {};
var map2 = {};
var map3 = {};
var map4 = {};

function populateInstructionMaps() {
    map[0x01] ="aconst_null";
    map[0x02] ="iconst_m1";
    map[0x03] ="iconst_0";
    map[0x04] ="iconst_1";
    map[0x05] ="iconst_2";
    map[0x06] ="iconst_3";
    map[0x07] ="iconst_4";
    map[0x08] ="iconst_5";
    map[0x09] ="lconst_0";
    map[0x0A] ="lconst_1";
    map[0x0B] ="fconst_0";
    map[0x0C] ="fconst_1";
    map[0x0D] ="fconst_2";
    map[0x0E] ="dconst_0";
    map[0x0F] ="dconst_1";
    map1[0x10] ="bipush";
    map2[0x11] ="sipush";
    map1[0x12] ="ldc";
    map2[0x13] ="ldc_w";
    map2[0x14] ="ldc2_w";
    map1[0x15] ="iload";
    map1[0x16] ="lload";
    map1[0x17] ="fload";
    map1[0x18] ="dload";
    map1[0x19] ="aload";
    map[0x1A] ="iload_0";
    map[0x1B] ="iload_1";
    map[0x1C] ="iload_2";
    map[0x1D] ="iload_3";
    map[0x1E] ="lload_0";
    map[0x1F] ="lload_1";
    map[0x20] ="lload_2";
    map[0x21] ="lload_3";
    map[0x22] ="fload_0";
    map[0x23] ="fload_1";
    map[0x24] ="fload_2";
    map[0x25] ="fload_3";
    map[0x26] ="dload_0";
    map[0x27] ="dload_1";
    map[0x28] ="dload_2";
    map[0x29] ="dload_3";
    map[0x2A] ="aload_0";
    map[0x2B] ="aload_1";
    map[0x2C] ="aload_2";
    map[0x2D] ="aload_3";
    map[0x2E] ="iaload";
    map[0x2F] ="laload";
    map[0x30] ="faload";
    map[0x31] ="daload";
    map[0x32] ="aaload";
    map[0x33] ="baload";
    map[0x34] ="caload";
    map[0x35] ="saload";
    map1[0x36] ="istore";
    map1[0x37] ="lstore";
    map1[0x38] ="fstore";
    map1[0x39] ="dstore";
    map1[0x3A] ="astore";
    map[0x3B] ="istore_0";
    map[0x3C] ="istore_1";
    map[0x3D] ="istore_2";
    map[0x3E] ="istore_3";
    map[0x3F] ="lstore_0";
    map[0x40] ="lstore_1";
    map[0x41] ="lstore_2";
    map[0x42] ="lstore_3";
    map[0x43] ="fstore_0";
    map[0x44] ="fstore_1";
    map[0x45] ="fstore_2";
    map[0x46] ="fstore_3";
    map[0x47] ="dstore_0";
    map[0x48] ="dstore_1";
    map[0x49] ="dstore_2";
    map[0x4A] ="dstore_3";
    map[0x4B] ="astore_0";
    map[0x4C] ="astore_1";
    map[0x4D] ="astore_2";
    map[0x4E] ="astore_3";
    map[0x4F] ="iastore";
    map[0x50] ="lastore";
    map[0x51] ="fastore";
    map[0x52] ="dastore";
    map[0x53] ="aastore";
    map[0x54] ="bastore";
    map[0x55] ="castore";
    map[0x56] ="sastore";
    map[0x57] ="pop";
    map[0x58] ="pop2";
    map[0x59] ="dup";
    map[0x5A] ="dup_x1";
    map[0x5B] ="dup_x2";
    map[0x5C] ="dup2";
    map[0x5D] ="dup2_x1";
    map[0x5E] ="dup2_x2";
    map[0x5F] ="swap";
    map[0x60] ="iadd";
    map[0x61] ="ladd";
    map[0x62] ="fadd";
    map[0x63] ="dadd";
    map[0x64] ="isub";
    map[0x65] ="lsub";
    map[0x66] ="fsub";
    map[0x67] ="dsub";
    map[0x68] ="imul";
    map[0x69] ="lmul";
    map[0x6A] ="fmul";
    map[0x6B] ="dmul";
    map[0x6C] ="idiv";
    map[0x6D] ="ldiv";
    map[0x6E] ="fdiv";
    map[0x6F] ="ddiv";
    map[0x70] ="irem";
    map[0x71] ="lrem";
    map[0x72] ="frem";
    map[0x73] ="drem";
    map[0x74] ="ineg";
    map[0x75] ="lneg";
    map[0x76] ="fneg";
    map[0x77] ="dneg";
    map[0x78] ="ishl";
    map[0x79] ="lshl";
    map[0x7A] ="ishr";
    map[0x7B] ="lshr";
    map[0x7C] ="iushr";
    map[0x7D] ="lushr";
    map[0x7E] ="iand";
    map[0x7F] ="land";
    map[0x80] ="ior";
    map[0x81] ="lor";
    map[0x82] ="ixor";
    map[0x83] ="lxor";
    map2[0x84] ="iinc";
    map[0x85] ="i2l";
    map[0x86] ="i2f";
    map[0x87] ="i2d";
    map[0x88] ="l2i";
    map[0x89] ="l2f";
    map[0x8A] ="l2d";
    map[0x8B] ="f2i";
    map[0x8C] ="f2l";
    map[0x8D] ="f2d";
    map[0x8E] ="d2i";
    map[0x8F] ="d2l";
    map[0x90] ="d2f";
    map[0x91] ="i2b";
    map[0x92] ="i2c";
    map[0x93] ="i2s";
    map[0x94] ="lcmp";
    map[0x95] ="fcmpl";
    map[0x96] ="fcmpg";
    map[0x97] ="dcmpl";
    map[0x98] ="dcmpg";
    map2[0x99] ="ifeq";
    map2[0x9A] ="ifne";
    map2[0x9B] ="iflt";
    map2[0x9C] ="ifge";
    map2[0x9D] ="ifgt";
    map2[0x9E] ="ifle";
    map2[0x9F] ="if_icmpeq";
    map2[0xA0] ="if_icmpne";
    map2[0xA1] ="if_icmplt";
    map2[0xA2] ="if_icmpge";
    map2[0xA3] ="if_icmpgt";
    map2[0xA4] ="if_icmple";
    map2[0xA5] ="if_acmpeq";
    map2[0xA6] ="if_acmpne";
    map2[0xA7] ="goto";
    map2[0xA8] ="jsr";
    map1[0xA9] ="ret";
//    map4+[0xAA] ="tableswitch";
//    map4+[0xAB] ="lookupswitch";
    map[0xAC] ="ireturn";
    map[0xAD] ="lreturn";
    map[0xAE] ="freturn";
    map[0xAF] ="dreturn";
    map[0xB0] ="areturn";
    map[0xB1] ="return";
    map2[0xB2] ="getstatic";
    map2[0xB3] ="putstatic";
    map2[0xB4] ="getfield";
    map2[0xB5] ="putfield";
    map2[0xB6] ="invokevirtual";
    map2[0xB7] ="invokespecial";
    map2[0xB8] ="invokestatic";
    map4[0xB9] ="invokeinterface";
    map4[0xBA] ="invokedynamic";
    map2[0xBB] ="new";
    map1[0xBC] ="newarray";
    map2[0xBD] ="anewarray";
    map[0xBE] ="arraylength";
    map[0xBF] ="athrow";
    map2[0xC0] ="checkcast";
    map2[0xC1] ="instanceof";
    map[0xC2] ="monitorenter";
    map[0xC3] ="monitorexit";
//    map42068[0xC4] ="wide";
    map3[0xC5] ="multianewarray";
    map2[0xC6] ="ifnull";
    map2[0xC7] ="ifnonnull";
    map4[0xC8] ="goto_w";
    map4[0xC9] ="jsr_w";
    map[0xCA] ="breakpoint";
    map[0xFD] ="(no name)";
    map[0xFE] ="impdep1";
    map[0xFF] ="impdep2";
}